{
  "mode": "NPL",
  "title": "부실채권(NPL) 상가",
  "count": 145,
  "npl": 145,
  "types": {
    "자산관리": 1,
    "유동화": 18,
    "대부": 2
  },
  "by_kw": {
    "채권승계": 124,
    "유동화": 18,
    "대부": 2,
    "자산관리": 1
  },
  "by_region": {
    "화성시": 23,
    "수원시": 15,
    "시흥시": 14,
    "평택시": 13,
    "김포시": 10,
    "하남시": 8,
    "고양시": 8,
    "안양시": 7,
    "안성시": 6,
    "오산시": 5,
    "부천시": 5,
    "안산시": 5,
    "파주시": 4,
    "남양주시": 4,
    "용인시": 3,
    "동두천시": 2,
    "이천시": 2,
    "기타": 2,
    "양주시": 2,
    "광명시": 2,
    "의정부시": 2,
    "광주시": 1,
    "성남시": 1,
    "포천시": 1
  },
  "avg_drate": 32,
  "top": [
    {
      "kw": "채권승계",
      "csno": "2024타경11589",
      "court": "수원지방법원",
      "addr": "경기도 수원시 권선구 경수대로409번길 17 6층601호",
      "gam": "147,000,000",
      "low": "147,000,000",
      "drate": 0,
      "yuchal": "1",
      "giil": "20260703",
      "npl": true,
      "types": [],
      "names": [
        "주식회사 하나은행"
      ]
    },
    {
      "kw": "채권승계",
      "csno": "2024타경12797",
      "court": "수원지방법원",
      "addr": "경기도 화성시 동탄기흥로 614 1층140호 (영천동,더퍼스트타워투)",
      "gam": "1,316,000,000",
      "low": "315,972,000",
      "drate": 76,
      "yuchal": "5",
      "giil": "20260703",
      "npl": true,
      "types": [],
      "names": [
        "주식회사 국민은행"
      ]
    },
    {
      "kw": "채권승계",
      "csno": "2024타경65906",
      "court": "수원지방법원",
      "addr": "경기도 화성시 삼성1로 144-13 1층103호",
      "gam": "1,080,000,000",
      "low": "370,440,000",
      "drate": 66,
      "yuchal": "4",
      "giil": "20260703",
      "npl": true,
      "types": [],
      "names": []
    },
    {
      "kw": "채권승계",
      "csno": "2025타경746",
      "court": "수원지방법원",
      "addr": "경기도 화성시 동탄감배산로 124-6 2층214호 (오산동,이너매스여울숲",
      "gam": "1,598,000,000",
      "low": "548,114,000",
      "drate": 66,
      "yuchal": "4",
      "giil": "20260703",
      "npl": true,
      "types": [],
      "names": [
        "주식회사 우리은행"
      ]
    },
    {
      "kw": "채권승계",
      "csno": "2025타경987",
      "court": "수원지방법원",
      "addr": "경기도 수원시 팔달구 인계동 1030-16 2층201호",
      "gam": "317,000,000",
      "low": "221,900,000",
      "drate": 30,
      "yuchal": "2",
      "giil": "20260703",
      "npl": true,
      "types": [],
      "names": [
        "주식회사 하나은행"
      ]
    },
    {
      "kw": "채권승계",
      "csno": "2025타경54259",
      "court": "수원지방법원",
      "addr": "경기도 오산시 수청동 611-4 물향기시티 1층103호",
      "gam": "790,000,000",
      "low": "387,100,000",
      "drate": 51,
      "yuchal": "3",
      "giil": "20260703",
      "npl": true,
      "types": [],
      "names": []
    },
    {
      "kw": "채권승계",
      "csno": "2025타경54994",
      "court": "수원지방법원",
      "addr": "경기도 화성시 능동 1063-4 세가프라자 1층109호",
      "gam": "416,000,000",
      "low": "291,200,000",
      "drate": 30,
      "yuchal": "2",
      "giil": "20260703",
      "npl": true,
      "types": [],
      "names": []
    },
    {
      "kw": "채권승계",
      "csno": "2025타경55061",
      "court": "수원지방법원",
      "addr": "경기도 수원시 권선구 권선동 1020-3 소노하임 1층102호",
      "gam": "850,000,000",
      "low": "595,000,000",
      "drate": 30,
      "yuchal": "2",
      "giil": "20260703",
      "npl": true,
      "types": [],
      "names": []
    }
  ],
  "file": "results_npl.html"
}